jsonlt/__init__.py
jsonlt/_constants.py
jsonlt/_encoding.py
jsonlt/_exceptions.py
jsonlt/_filesystem.py
jsonlt/_header.py
jsonlt/_json.py
jsonlt/_keys.py
jsonlt/_lock.py
jsonlt/_readable.py
jsonlt/_reader.py
jsonlt/_records.py
jsonlt/_state.py
jsonlt/_table.py
jsonlt/_transaction.py
jsonlt/_writer.py
jsonlt/py.typed
jsonlt_python-0.1.0.dist-info/WHEEL
jsonlt_python-0.1.0.dist-info/METADATA
jsonlt_python-0.1.0.dist-info/RECORD
