Metadata-Version: 2.4
Name: jsonlt-python
Version: 0.1.0
Summary: Reference implementation of the JSONLT (JSON Lines Table) specification for Python.
Keywords: append-only,data-format,database,json-lines,jsonl,jsonlines,jsonlt,version-control
License-Expression: MIT
Classifier: Development Status :: 3 - Alpha
Classifier: Intended Audience :: Developers
Classifier: License :: OSI Approved :: MIT License
Classifier: Operating System :: OS Independent
Classifier: Programming Language :: Python :: 3
Classifier: Programming Language :: Python :: 3.10
Classifier: Programming Language :: Python :: 3.11
Classifier: Programming Language :: Python :: 3.12
Classifier: Programming Language :: Python :: 3.13
Classifier: Programming Language :: Python :: 3.14
Classifier: Programming Language :: Python :: Free Threading :: 1 - Unstable
Classifier: Topic :: Database
Classifier: Topic :: File Formats :: JSON
Classifier: Topic :: Software Development :: Libraries :: Python Modules
Classifier: Typing :: Typed
Requires-Dist: typing-extensions>=4.15.0
Requires-Python: >=3.10
Project-URL: Changelog, https://github.com/jsonlt/jsonlt-python/blob/main/CHANGELOG.md
Project-URL: Documentation, https://jsonlt.org/docs
Project-URL: Homepage, https://jsonlt.org
Project-URL: Issues, https://github.com/jsonlt/jsonlt-python/issues
Project-URL: Repository, https://github.com/jsonlt/jsonlt-python
